README.rst
setup.py
python_speech_features/__init__.py
python_speech_features/base.py
python_speech_features/sigproc.py
python_speech_features.egg-info/PKG-INFO
python_speech_features.egg-info/SOURCES.txt
python_speech_features.egg-info/dependency_links.txt
python_speech_features.egg-info/top_level.txt