Metadata-Version: 1.0
Name: python-speech-features
Version: 0.5
Summary: Python Speech Feature extraction
Home-page: https://github.com/jameslyons/python_speech_features
Author: James Lyons
Author-email: james.lyons0@gmail.com
License: MIT
Platform: UNKNOWN
